{
  "generated_at_utc": "2026-03-12T22:56:21.282380+00:00",
  "generated_at_epoch_ms": 1773356181282,
  "active_days": 14,
  "min_value": 500000.0,
  "source": {
    "info_url": "https://api.hyperliquid.xyz/info",
    "leaderboard_url": "https://stats-data.hyperliquid.xyz/Mainnet/leaderboard"
  },
  "notes": {
    "pnl_pct_and_growth_pct_are_approx": true,
    "reason": "Computed from portfolio accountValueHistory/pnlHistory deltas divided by start account value."
  },
  "failed_states": [],
  "failed_fills": [
    "0x4ed0b41dff79e0e53a054903873899bc32abc853",
    "0x308ac0b8de9699b754e72a568f143d8856993336",
    "0x77435010f5e34e2fa04f5ce7d49e57a8bd8de4fe"
  ],
  "files": [
    "active_all.json",
    "active_risk.json",
    "active_pnl.json",
    "active_stability.json",
    "active_conviction.json"
  ]
}