{
  "generated_at_utc": "2026-02-11T15:24:25.117892+00:00",
  "generated_at_epoch_ms": 1770823465117,
  "active_days": 14,
  "min_value": 500000.0,
  "source": {
    "info_url": "https://api.hyperliquid.xyz/info",
    "leaderboard_url": "https://stats-data.hyperliquid.xyz/Mainnet/leaderboard"
  },
  "notes": {
    "pnl_pct_and_growth_pct_are_approx": true,
    "reason": "Computed from portfolio accountValueHistory/pnlHistory deltas divided by start account value."
  },
  "failed_states": [],
  "failed_fills": [
    "0xd47587702a91731dc1089b5db0932cf820151a91",
    "0x24fb6523036ebcb3cc51deff138066dccf6bed0f",
    "0x936cf4fb95c30ce83f658b5bbb247e4bb381bb0f",
    "0x064e89061ce80cb1b41a2d2963d48d2e8cabde4a",
    "0xe7ec7fbf4f195fc8e57d814e15c3a2857cb632a3",
    "0xa9b91ec3cd32ba4e5841b2bf6ec5d2c222e60243"
  ],
  "files": [
    "active_all.json",
    "active_risk.json",
    "active_pnl.json",
    "active_stability.json",
    "active_conviction.json"
  ]
}