{
  "generated_at_utc": "2026-05-19T19:30:14.193825+00:00",
  "generated_at_epoch_ms": 1779219014193,
  "active_days": 14,
  "min_value": 500000.0,
  "source": {
    "info_url": "https://api.hyperliquid.xyz/info",
    "leaderboard_url": "https://stats-data.hyperliquid.xyz/Mainnet/leaderboard"
  },
  "notes": {
    "pnl_pct_and_growth_pct_are_approx": true,
    "reason": "Computed from portfolio accountValueHistory/pnlHistory deltas divided by start account value."
  },
  "failed_states": [],
  "failed_fills": [
    "0x2d66f73159eaa54cc7fddaea2ba8cf91f9f14cd6",
    "0xd83cff88a32ffbf3951f2b13e4a0a37103b3193d",
    "0x4e23288cee4960f9f962195c22948e4bc7ae20c3"
  ],
  "files": [
    "active_all.json",
    "active_risk.json",
    "active_pnl.json",
    "active_stability.json",
    "active_conviction.json"
  ]
}